jitbf.py
jitbf-1.0.1.dist-info/METADATA
jitbf-1.0.1.dist-info/WHEEL
jitbf-1.0.1.dist-info/entry_points.txt
jitbf-1.0.1.dist-info/top_level.txt
jitbf-1.0.1.dist-info/RECORD
