Metadata-Version: 2.1
Name: jitbf
Version: 1.0.1
Summary: Brainfuck JIT interpreter in Python
Home-page: https://github.com/none-None1/jitbf
Keywords: brainfuck,jit-interpreter,llvm
Classifier: Operating System :: OS Independent
Classifier: Programming Language :: Python :: 3 :: Only
Classifier: Topic :: Software Development :: Interpreters
Requires-Python: >=3
